rpi_derive_key-0.2.1.dist-info/METADATA
rpi_derive_key-0.2.1.dist-info/WHEEL
rpi_derive_key/__init__.py
rpi_derive_key/__init__.pyi
rpi_derive_key/py.typed
rpi_derive_key/rpi_derive_key.pyd
rpi_derive_key-0.2.1.dist-info/RECORD
