Metadata-Version: 2.1
Name: rpi_derive_key
Version: 0.2.1
Classifier: Programming Language :: Rust
Classifier: Programming Language :: Python :: Implementation :: CPython
Classifier: Programming Language :: Python :: Implementation :: PyPy
Author: Silitics GmbH <info@silitics.com>
Author-email: Silitics GmbH <info@silitics.com>
License: MIT OR Apache-2.0
Requires-Python: >=3.7
Project-URL: Source Code, https://github.com/silitics/rpi-derive-key
